{
    "caddy-core": {
        "cargoLocks": null,
        "date": null,
        "extract": null,
        "name": "caddy-core",
        "passthru": null,
        "pinned": false,
        "src": {
            "deepClone": false,
            "fetchSubmodules": false,
            "leaveDotGit": false,
            "name": null,
            "owner": "caddyserver",
            "repo": "caddy",
            "rev": "v2.9.1",
            "sha256": "sha256-XW1cBW7mk/aO/3IPQK29s4a6ArSKjo7/64koJuzp07I=",
            "sparseCheckout": [],
            "type": "github"
        },
        "version": "v2.9.1"
    },
    "caddy-plugin-cloudflare": {
        "cargoLocks": null,
        "date": "2025-02-28",
        "extract": null,
        "name": "caddy-plugin-cloudflare",
        "passthru": null,
        "pinned": false,
        "src": {
            "deepClone": false,
            "fetchSubmodules": false,
            "leaveDotGit": false,
            "name": null,
            "owner": "caddy-dns",
            "repo": "cloudflare",
            "rev": "1fb64108d4debf196b19d7398e763cb78c8a0f41",
            "sha256": "sha256-nLpiXMHTKTfmc5TBkPErkvXf/d2tWBlv2h4A+ELrraU=",
            "sparseCheckout": [],
            "type": "github"
        },
        "version": "1fb64108d4debf196b19d7398e763cb78c8a0f41"
    },
    "kubecolor-catppuccin": {
        "cargoLocks": null,
        "date": "2024-05-24",
        "extract": null,
        "name": "kubecolor-catppuccin",
        "passthru": null,
        "pinned": false,
        "src": {
            "deepClone": false,
            "fetchSubmodules": false,
            "leaveDotGit": false,
            "name": null,
            "owner": "vkhitrin",
            "repo": "kubecolor-catppuccin",
            "rev": "1d4c2888f7de077e1a837a914a1824873d16762d",
            "sha256": "sha256-gTneUh6yMcH6dVKrH00G61a+apasu9tiMyYjvNdOiOw=",
            "sparseCheckout": [],
            "type": "github"
        },
        "version": "1d4c2888f7de077e1a837a914a1824873d16762d"
    },
    "kubectl-pgo": {
        "cargoLocks": null,
        "date": null,
        "extract": null,
        "name": "kubectl-pgo",
        "passthru": null,
        "pinned": false,
        "src": {
            "deepClone": false,
            "fetchSubmodules": false,
            "leaveDotGit": false,
            "name": null,
            "owner": "CrunchyData",
            "repo": "postgres-operator-client",
            "rev": "v0.5.1",
            "sha256": "sha256-0y1+goq9xFZYfHelUBJD/ZcEiDvRFx0sEweF1Q6N2uk=",
            "sparseCheckout": [],
            "type": "github"
        },
        "version": "v0.5.1"
    },
    "talos-api": {
        "cargoLocks": null,
        "date": null,
        "extract": null,
        "name": "talos-api",
        "passthru": null,
        "pinned": false,
        "src": {
            "deepClone": false,
            "fetchSubmodules": false,
            "leaveDotGit": false,
            "name": null,
            "owner": "siderolabs",
            "repo": "discovery-service",
            "rev": "v1.0.10",
            "sha256": "sha256-d0aSBtjfSctXn7repf0FwC53zG/9aSnvHRMZpiXCwuA=",
            "sparseCheckout": [],
            "type": "github"
        },
        "version": "v1.0.10"
    },
    "talosctl": {
        "cargoLocks": null,
        "date": null,
        "extract": null,
        "name": "talosctl",
        "passthru": null,
        "pinned": false,
        "src": {
            "deepClone": false,
            "fetchSubmodules": false,
            "leaveDotGit": false,
            "name": null,
            "owner": "siderolabs",
            "repo": "talos",
            "rev": "v1.9.5",
            "sha256": "sha256-2YKZfW62yOA8uV3bn6at/9YV3OHjiMuqA1SUupyAAx4=",
            "sparseCheckout": [],
            "type": "github"
        },
        "version": "v1.9.5"
    },
    "zotregistry": {
        "cargoLocks": null,
        "date": null,
        "extract": null,
        "name": "zotregistry",
        "passthru": null,
        "pinned": false,
        "src": {
            "deepClone": false,
            "fetchSubmodules": false,
            "leaveDotGit": false,
            "name": null,
            "owner": "project-zot",
            "repo": "zot",
            "rev": "v2.1.2",
            "sha256": "sha256-tVvqNA7imLmVQoO7giEtktJkgQTaaWjkB/aYM+or6kg=",
            "sparseCheckout": [],
            "type": "github"
        },
        "version": "v2.1.2"
    },
    "zotregistry-ui": {
        "cargoLocks": null,
        "date": "2025-03-24",
        "extract": null,
        "name": "zotregistry-ui",
        "passthru": null,
        "pinned": true,
        "src": {
            "deepClone": false,
            "fetchSubmodules": false,
            "leaveDotGit": false,
            "name": null,
            "owner": "project-zot",
            "repo": "zui",
            "rev": "303dfb3253172babb179a2752f146d9e93081897",
            "sha256": "sha256-J0c/kkM8hkSkzVWXhUCxKKz2zujkuGLrOMb4kpygpkY=",
            "sparseCheckout": [],
            "type": "github"
        },
        "version": "303dfb3253172babb179a2752f146d9e93081897"
    }
}